ephemeral_pulumi_deploy/__init__.py
ephemeral_pulumi_deploy/cli.py
ephemeral_pulumi_deploy/py.typed
ephemeral_pulumi_deploy/utils.py
ephemeral_pulumi_deploy-0.0.6.dist-info/METADATA
ephemeral_pulumi_deploy-0.0.6.dist-info/WHEEL
ephemeral_pulumi_deploy-0.0.6.dist-info/top_level.txt
ephemeral_pulumi_deploy-0.0.6.dist-info/RECORD
