Metadata-Version: 2.4
Name: ephemeral-pulumi-deploy
Version: 0.0.6
Summary: Library for facilitating easy deployment of ephemeral pulumi stacks
Author: Eli Fine
Classifier: Programming Language :: Python :: 3
Classifier: Programming Language :: Python :: 3.12
Classifier: Programming Language :: Python :: 3.13
Classifier: Programming Language :: Python :: 3.14
Requires-Python: >=3.12.7
Requires-Dist: pulumi>=3.213.0
Requires-Dist: pulumi-aws>=7.15.0
Requires-Dist: pulumi-aws-native>=1.45.0
Requires-Dist: boto3>=1.42.14
